aiotorndb.py
aiotorndb-0.2.dist-info/LICENSE
aiotorndb-0.2.dist-info/METADATA
aiotorndb-0.2.dist-info/WHEEL
aiotorndb-0.2.dist-info/top_level.txt
aiotorndb-0.2.dist-info/RECORD
