Metadata-Version: 2.1
Name: aiotorndb
Version: 0.2
Summary: asynchronous tornado database connection
Author-email: ResistanceTo <resistanceto@outlook.com>
Project-URL: Homepage, https://github.com/ResistanceTo/aiotorndb
Project-URL: Bug Tracker, https://github.com/ResistanceTo/aiotorndb/issues
Classifier: Intended Audience :: Developers
Classifier: License :: OSI Approved :: MIT License
Classifier: Operating System :: OS Independent
Classifier: Programming Language :: Python :: 3.7
Classifier: Programming Language :: Python :: 3.8
Classifier: Programming Language :: Python :: 3.9
Classifier: Programming Language :: Python :: 3.10
Classifier: Topic :: Software Development :: Libraries
Requires-Python: >=3.7
License-File: LICENSE
